01-toprammer-udev.rules
COPYING
MANIFEST.in
README-DEVELOPERS.lyx
README-DEVELOPERS.ps
README.lyx
README.ps
RUNTIME_IDS
requirements.txt
setup.py
toprammer
toprammer-gui
toprammer-layout
libtoprammer/__init__.py
libtoprammer/bitfile.py
libtoprammer/chip.py
libtoprammer/command_queue.py
libtoprammer/generic_algorithms.py
libtoprammer/generic_layout.py
libtoprammer/hardware_access_usb.py
libtoprammer/ihex.py
libtoprammer/layout_generator.py
libtoprammer/main.py
libtoprammer/shiftreg_layout.py
libtoprammer/top_devices.py
libtoprammer/user_interface.py
libtoprammer/util.py
libtoprammer/chips/_27cxxx.py
libtoprammer/chips/_74hc4094.py
libtoprammer/chips/__init__.py
libtoprammer/chips/at89c2051dip20.py
libtoprammer/chips/at89s51dip40.py
libtoprammer/chips/at89s52dip40.py
libtoprammer/chips/atmega168dip28.py
libtoprammer/chips/atmega328dip28.py
libtoprammer/chips/atmega32dip40.py
libtoprammer/chips/atmega48dip28.py
libtoprammer/chips/atmega88dip28.py
libtoprammer/chips/atmega8dip28.py
libtoprammer/chips/atmega_common.py
libtoprammer/chips/attiny13dip8.py
libtoprammer/chips/attiny25dip8.py
libtoprammer/chips/attiny26dip20.py
libtoprammer/chips/attiny45dip8.py
libtoprammer/chips/attiny85dip8.py
libtoprammer/chips/attinyspc_common.py
libtoprammer/chips/generic_sram.py
libtoprammer/chips/hm62256dip28.py
libtoprammer/chips/m24cxxdip8.py
libtoprammer/chips/m8cissp.py
libtoprammer/chips/unitest.py
libtoprammer/chips/w29ee011dip32.py
libtoprammer/chips/microchip16/__init__.py
libtoprammer/chips/microchip16/configWords.py
libtoprammer/chips/microchip16/makeSip6.py
libtoprammer/chips/microchip16/microchip16_common.py
libtoprammer/chips/microchip16/pic24f04ka200dip14.py
libtoprammer/chips/microchip16/pic24f04ka200sip6.py
libtoprammer/chips/microchip16/pic24f04ka201dip20.py
libtoprammer/chips/microchip16/pic24f04ka201sip6.py
libtoprammer/chips/microchip16/pic24f04kl100dip14.py
libtoprammer/chips/microchip16/pic24f04kl100sip6.py
libtoprammer/chips/microchip16/pic24f04kl101dip20.py
toprammer.egg-info/PKG-INFO
toprammer.egg-info/SOURCES.txt
toprammer.egg-info/dependency_links.txt
toprammer.egg-info/requires.txt
toprammer.egg-info/top_level.txt